[
    {
        "key": "dbln",
        "value": "%7B%22100093062719419%22%3A%22Q2YuD2v1%22%7D",
        "domain": "facebook.com",
        "path": "/login/device-based/",
        "hostOnly": false,
        "creation": "2024-09-08T17:06:57.601Z",
        "lastAccessed": "2024-09-08T17:06:57.601Z"
    },
    {
        "key": "sb",
        "value": "jxkTZssU5qeL-Ijg1r71xUC2",
        "domain": "facebook.com",
        "path": "/",
        "hostOnly": false,
        "creation": "2024-09-08T17:06:57.601Z",
        "lastAccessed": "2024-09-08T17:06:57.601Z"
    },
    {
        "key": "ps_n",
        "value": "1",
        "domain": "facebook.com",
        "path": "/",
        "hostOnly": false,
        "creation": "2024-09-08T17:06:57.601Z",
        "lastAccessed": "2024-09-08T17:06:57.601Z"
    },
    {
        "key": "ps_l",
        "value": "1",
        "domain": "facebook.com",
        "path": "/",
        "hostOnly": false,
        "creation": "2024-09-08T17:06:57.601Z",
        "lastAccessed": "2024-09-08T17:06:57.601Z"
    },
    {
        "key": "vpd",
        "value": "v1%3B668x360x2",
        "domain": "facebook.com",
        "path": "/",
        "hostOnly": false,
        "creation": "2024-09-08T17:06:57.601Z",
        "lastAccessed": "2024-09-08T17:06:57.601Z"
    },
    {
        "key": "wl_cbv",
        "value": "v2%3Bclient_version%3A2563%3Btimestamp%3A1720990845",
        "domain": "facebook.com",
        "path": "/",
        "hostOnly": false,
        "creation": "2024-09-08T17:06:57.601Z",
        "lastAccessed": "2024-09-08T17:06:57.601Z"
    },
    {
        "key": "dpr",
        "value": "2.1988937854766846",
        "domain": "facebook.com",
        "path": "/",
        "hostOnly": false,
        "creation": "2024-09-08T17:06:57.601Z",
        "lastAccessed": "2024-09-08T17:06:57.601Z"
    },
    {
        "key": "locale",
        "value": "en_US",
        "domain": "facebook.com",
        "path": "/",
        "hostOnly": false,
        "creation": "2024-09-08T17:06:57.601Z",
        "lastAccessed": "2024-09-08T17:06:57.601Z"
    },
    {
        "key": "c_user",
        "value": "100093062719419",
        "domain": "facebook.com",
        "path": "/",
        "hostOnly": false,
        "creation": "2024-09-08T17:06:57.601Z",
        "lastAccessed": "2024-09-08T17:06:57.601Z"
    },
    {
        "key": "datr",
        "value": "kNPdZjkR6SDZL5-KfNc5MFaS",
        "domain": "facebook.com",
        "path": "/",
        "hostOnly": false,
        "creation": "2024-09-08T17:06:57.601Z",
        "lastAccessed": "2024-09-08T17:06:57.601Z"
    },
    {
        "key": "wd",
        "value": "891x1654",
        "domain": "facebook.com",
        "path": "/",
        "hostOnly": false,
        "creation": "2024-09-08T17:06:57.601Z",
        "lastAccessed": "2024-09-08T17:06:57.601Z"
    },
    {
        "key": "xs",
        "value": "21%3AGvD755ZKmbwyKQ%3A2%3A1725813646%3A-1%3A7256%3A%3AAcUqhmRz-pON7aoSlpFEVDn_kmqxPZEx6kTrL4bYLQ",
        "domain": "facebook.com",
        "path": "/",
        "hostOnly": false,
        "creation": "2024-09-08T17:06:57.601Z",
        "lastAccessed": "2024-09-08T17:06:57.601Z"
    },
    {
        "key": "fr",
        "value": "1maV5cSH0EEHSxj77.AWWYmL3EQEY8RM8YjEZtWYGTcxU.Bm3dVt..AAA.0.0.Bm3dms.AWXe0ympYj4",
        "domain": "facebook.com",
        "path": "/",
        "hostOnly": false,
        "creation": "2024-09-08T17:06:57.601Z",
        "lastAccessed": "2024-09-08T17:06:57.601Z"
    }
]
