[
    {
        "key": "dbln",
        "value": "%7B%2261564124272934%22%3A%22NmOrVIeH%22%7D",
        "domain": "facebook.com",
        "path": "/login/device-based/",
        "hostOnly": false,
        "creation": "2024-08-08T13:41:03.039Z",
        "lastAccessed": "2024-08-08T13:41:03.040Z"
    },
    {
        "key": "sb",
        "value": "jxkTZssU5qeL-Ijg1r71xUC2",
        "domain": "facebook.com",
        "path": "/",
        "hostOnly": false,
        "creation": "2024-08-08T13:41:03.040Z",
        "lastAccessed": "2024-08-08T13:41:03.040Z"
    },
    {
        "key": "ps_n",
        "value": "1",
        "domain": "facebook.com",
        "path": "/",
        "hostOnly": false,
        "creation": "2024-08-08T13:41:03.040Z",
        "lastAccessed": "2024-08-08T13:41:03.040Z"
    },
    {
        "key": "ps_l",
        "value": "1",
        "domain": "facebook.com",
        "path": "/",
        "hostOnly": false,
        "creation": "2024-08-08T13:41:03.040Z",
        "lastAccessed": "2024-08-08T13:41:03.040Z"
    },
    {
        "key": "vpd",
        "value": "v1%3B668x360x2",
        "domain": "facebook.com",
        "path": "/",
        "hostOnly": false,
        "creation": "2024-08-08T13:41:03.040Z",
        "lastAccessed": "2024-08-08T13:41:03.040Z"
    },
    {
        "key": "wl_cbv",
        "value": "v2%3Bclient_version%3A2563%3Btimestamp%3A1720990845",
        "domain": "facebook.com",
        "path": "/",
        "hostOnly": false,
        "creation": "2024-08-08T13:41:03.040Z",
        "lastAccessed": "2024-08-08T13:41:03.040Z"
    },
    {
        "key": "dpr",
        "value": "2.1988937854766846",
        "domain": "facebook.com",
        "path": "/",
        "hostOnly": false,
        "creation": "2024-08-08T13:41:03.040Z",
        "lastAccessed": "2024-08-08T13:41:03.040Z"
    },
    {
        "key": "datr",
        "value": "7SquZvUC-GbXvtzsZYuhEOih",
        "domain": "facebook.com",
        "path": "/",
        "hostOnly": false,
        "creation": "2024-08-08T13:41:03.040Z",
        "lastAccessed": "2024-08-08T13:41:03.040Z"
    },
    {
        "key": "locale",
        "value": "en_US",
        "domain": "facebook.com",
        "path": "/",
        "hostOnly": false,
        "creation": "2024-08-08T13:41:03.040Z",
        "lastAccessed": "2024-08-08T13:41:03.040Z"
    },
    {
        "key": "wd",
        "value": "891x1654",
        "domain": "facebook.com",
        "path": "/",
        "hostOnly": false,
        "creation": "2024-08-08T13:41:03.040Z",
        "lastAccessed": "2024-08-08T13:41:03.040Z"
    },
    {
        "key": "c_user",
        "value": "100093062719419",
        "domain": "facebook.com",
        "path": "/",
        "hostOnly": false,
        "creation": "2024-08-08T13:41:03.040Z",
        "lastAccessed": "2024-08-08T13:41:03.040Z"
    },
    {
        "key": "xs",
        "value": "33%3Ac5XsHoLxjxEX0w%3A2%3A1723124447%3A-1%3A11289",
        "domain": "facebook.com",
        "path": "/",
        "hostOnly": false,
        "creation": "2024-08-08T13:41:03.040Z",
        "lastAccessed": "2024-08-08T13:41:03.040Z"
    },
    {
        "key": "fr",
        "value": "1PFBKJTqyWyP5m0Og.AWUROoy4fcda2Ba03f2FqDiD-wI.BmtMPj..AAA.0.0.BmtMrh.AWV1R02zw54",
        "domain": "facebook.com",
        "path": "/",
        "hostOnly": false,
        "creation": "2024-08-08T13:41:03.040Z",
        "lastAccessed": "2024-08-08T13:41:03.040Z"
    },
    {
        "key": "presence",
        "value": "C%7B%22t3%22%3A%5B%5D%2C%22utc3%22%3A1723124460769%2C%22v%22%3A1%7D",
        "domain": "facebook.com",
        "path": "/",
        "hostOnly": false,
        "creation": "2024-08-08T13:41:03.040Z",
        "lastAccessed": "2024-08-08T13:41:03.040Z"
    }
]
