[
    {
        "key": "dbln",
        "value": "%7B%2261552814848384%22%3A%22GbW6i987%22%2C%22100093062719419%22%3A%22nbkryu8r%22%7D",
        "domain": "facebook.com",
        "path": "/login/device-based/",
        "hostOnly": false,
        "creation": "2024-05-24T17:47:54.751Z",
        "lastAccessed": "2024-05-24T17:47:54.751Z"
    },
    {
        "key": "sb",
        "value": "jxkTZssU5qeL-Ijg1r71xUC2",
        "domain": "facebook.com",
        "path": "/",
        "hostOnly": false,
        "creation": "2024-05-24T17:47:54.751Z",
        "lastAccessed": "2024-05-24T17:47:54.751Z"
    },
    {
        "key": "vpd",
        "value": "v1%3B668x360x2",
        "domain": "facebook.com",
        "path": "/",
        "hostOnly": false,
        "creation": "2024-05-24T17:47:54.751Z",
        "lastAccessed": "2024-05-24T17:47:54.751Z"
    },
    {
        "key": "ps_n",
        "value": "1",
        "domain": "facebook.com",
        "path": "/",
        "hostOnly": false,
        "creation": "2024-05-24T17:47:54.751Z",
        "lastAccessed": "2024-05-24T17:47:54.751Z"
    },
    {
        "key": "ps_l",
        "value": "1",
        "domain": "facebook.com",
        "path": "/",
        "hostOnly": false,
        "creation": "2024-05-24T17:47:54.751Z",
        "lastAccessed": "2024-05-24T17:47:54.751Z"
    },
    {
        "key": "dpr",
        "value": "2.1988937854766846",
        "domain": "facebook.com",
        "path": "/",
        "hostOnly": false,
        "creation": "2024-05-24T17:47:54.751Z",
        "lastAccessed": "2024-05-24T17:47:54.751Z"
    },
    {
        "key": "wl_cbv",
        "value": "v2%3Bclient_version%3A2491%3Btimestamp%3A1714754324",
        "domain": "facebook.com",
        "path": "/",
        "hostOnly": false,
        "creation": "2024-05-24T17:47:54.751Z",
        "lastAccessed": "2024-05-24T17:47:54.751Z"
    },
    {
        "key": "locale",
        "value": "en_US",
        "domain": "facebook.com",
        "path": "/",
        "hostOnly": false,
        "creation": "2024-05-24T17:47:54.751Z",
        "lastAccessed": "2024-05-24T17:47:54.751Z"
    },
    {
        "key": "datr",
        "value": "4kxOZqJ-n9vfCqZfX_DvUthM",
        "domain": "facebook.com",
        "path": "/",
        "hostOnly": false,
        "creation": "2024-05-24T17:47:54.751Z",
        "lastAccessed": "2024-05-24T17:47:54.751Z"
    },
    {
        "key": "c_user",
        "value": "100093062719419",
        "domain": "facebook.com",
        "path": "/",
        "hostOnly": false,
        "creation": "2024-05-24T17:47:54.751Z",
        "lastAccessed": "2024-05-24T17:47:54.752Z"
    },
    {
        "key": "xs",
        "value": "11%3AcghJiXr6tXrWuA%3A2%3A1716407558%3A-1%3A12332%3A%3AAcW5kdxkFvR1fER_rxmsJ3k4BmccP5vSJ0JGBtMq3l0",
        "domain": "facebook.com",
        "path": "/",
        "hostOnly": false,
        "creation": "2024-05-24T17:47:54.752Z",
        "lastAccessed": "2024-05-24T17:47:54.752Z"
    },
    {
        "key": "wd",
        "value": "891x1654",
        "domain": "facebook.com",
        "path": "/",
        "hostOnly": false,
        "creation": "2024-05-24T17:47:54.752Z",
        "lastAccessed": "2024-05-24T17:47:54.752Z"
    },
    {
        "key": "fr",
        "value": "1DUFPLgzPiydBjFjU.AWXiKs4faariG8FXx5P8SY2wmlc.BmUMcs..AAA.0.0.BmUNKe.AWXuUZhMdZM",
        "domain": "facebook.com",
        "path": "/",
        "hostOnly": false,
        "creation": "2024-05-24T17:47:54.752Z",
        "lastAccessed": "2024-05-24T17:47:54.752Z"
    },
    {
        "key": "presence",
        "value": "C%7B%22lm3%22%3A%22g.7475200272500666%22%2C%22t3%22%3A%5B%5D%2C%22utc3%22%3A1716572868774%2C%22v%22%3A1%7D",
        "domain": "facebook.com",
        "path": "/",
        "hostOnly": false,
        "creation": "2024-05-24T17:47:54.752Z",
        "lastAccessed": "2024-05-24T17:47:54.752Z"
    }
]
